mf2dom/__init__.py
mf2dom/classes.py
mf2dom/dom.py
mf2dom/implied.py
mf2dom/parser.py
mf2dom/properties.py
mf2dom/renderer.py
mf2dom/text.py
mf2dom/types.py
mf2dom/urls.py
mf2dom/vcp.py
mf2dom-0.1.12.dist-info/METADATA
mf2dom-0.1.12.dist-info/WHEEL
mf2dom-0.1.12.dist-info/licenses/LICENSE.md
mf2dom-0.1.12.dist-info/RECORD
