Metadata-Version: 2.4
Name: mf2dom
Version: 0.1.12
Summary: Microformats2 (mf2) parser and renderer powered by JustHTML.
Author-email: Beto Dealmeida <contact@robida.net>
License-File: LICENSE.md
Requires-Python: >=3.11
Requires-Dist: justhtml>=0.12.0
